shodan_downloader/__init__.py
shodan_downloader/cli.py
shodan_downloader/constants.py
shodan_downloader/core.py
shodan_downloader/utils.py
tests/__init__.py
tests/test_core.py
tests/test_utils.py
shodan_downloader-0.1.1.dist-info/METADATA
shodan_downloader-0.1.1.dist-info/WHEEL
shodan_downloader-0.1.1.dist-info/entry_points.txt
shodan_downloader-0.1.1.dist-info/top_level.txt
shodan_downloader-0.1.1.dist-info/RECORD
