Metadata-Version: 2.4
Name: shodan_downloader
Version: 0.1.1
Summary: A Python tool for searching Shodan and downloading filtered results.
Author-email: Luppa <102318505+Luppa90@users.noreply.github.com>
Requires-Python: >=3.7
Requires-Dist: shodan>=1.28.0
Requires-Dist: requests>=2.0.0
Requires-Dist: tqdm>=4.67.1
Dynamic: requires-python
